{"xhauflair": {"apellido": "XHAUFLAIR", "comunas": [{"comuna": "CHILLAN", "region": "16. REGION DE ÑUBLE", "provincia": "Diguillín", "totalapellido": 1, "totalcomuna": 152723, "prct_apellido": 7e-06, "freq_prov": 0.065041, "freq_reg": 0.0859, "cod_comuna": "16101"}]}, "xhemale": {"apellido": "XHEMALE", "comunas": [{"comuna": "SAN MIGUEL", "region": "13. REGION METROPOLITANA DE SANTIAGO", "provincia": "Santiago", "totalapellido": 3, "totalcomuna": 105090, "prct_apellido": 2.9e-05, "freq_prov": 0.017023, "freq_reg": 0.018986, "cod_comuna": "13130"}, {"comuna": "ÑUÑOA", "region": "13. REGION METROPOLITANA DE SANTIAGO", "provincia": "Santiago", "totalapellido": 6, "totalcomuna": 197198, "prct_apellido": 3e-05, "freq_prov": 0.017023, "freq_reg": 0.018986, "cod_comuna": "13120"}]}, "xhemali": {"apellido": "XHEMALI", "comunas": [{"comuna": "SANTIAGO", "region": "13. REGION METROPOLITANA DE SANTIAGO", "provincia": "Santiago", "totalapellido": 1, "totalcomuna": 340282, "prct_apellido": 3e-06, "freq_prov": 0.017023, "freq_reg": 0.018986, "cod_comuna": "13101"}]}}