{"kvammen": {"apellido": "KVAMMEN", "comunas": [{"comuna": "PROVIDENCIA", "region": "13. REGION METROPOLITANA DE SANTIAGO", "provincia": "Santiago", "totalapellido": 1, "totalcomuna": 170255, "prct_apellido": 0.0006, "freq_prov": 0.017023, "freq_reg": 0.018986, "cod_comuna": "13123"}]}, "kvamsas": {"apellido": "KVAMSAS", "comunas": [{"comuna": "ÑUÑOA", "region": "13. REGION METROPOLITANA DE SANTIAGO", "provincia": "Santiago", "totalapellido": 1, "totalcomuna": 197198, "prct_apellido": 0.0005, "freq_prov": 0.017023, "freq_reg": 0.018986, "cod_comuna": "13120"}]}, "kvapil": {"apellido": "KVAPIL", "comunas": [{"comuna": "EL TABO", "region": "05. REGION DE VALPARAISO", "provincia": "San Antonio", "totalapellido": 1, "totalcomuna": 11931, "prct_apellido": 0.0084, "freq_prov": 0.076723, "freq_reg": 0.029341, "cod_comuna": "05605"}, {"comuna": "CURICO", "region": "07. REGION DEL MAULE", "provincia": "Curicó", "totalapellido": 3, "totalcomuna": 117810, "prct_apellido": 0.0025, "freq_prov": 0.081137, "freq_reg": 0.082553, "cod_comuna": "07301"}, {"comuna": "VALDIVIA", "region": "14. REGION DE LOS RIOS", "provincia": "Valdivia", "totalapellido": 3, "totalcomuna": 138619, "prct_apellido": 0.0022, "freq_prov": 0.046113, "freq_reg": 0.0544, "cod_comuna": "14101"}, {"comuna": "PROVIDENCIA", "region": "13. REGION METROPOLITANA DE SANTIAGO", "provincia": "Santiago", "totalapellido": 3, "totalcomuna": 170255, "prct_apellido": 0.0018, "freq_prov": 0.017023, "freq_reg": 0.018986, "cod_comuna": "13123"}, {"comuna": "TEMUCO", "region": "09. REGION DE LA ARAUCANIA", "provincia": "Cautín", "totalapellido": 2, "totalcomuna": 236909, "prct_apellido": 0.0008, "freq_prov": 0.043946, "freq_reg": 0.051873, "cod_comuna": "09101"}]}, "kvasov": {"apellido": "KVASOV", "comunas": [{"comuna": "SANTIAGO", "region": "13. REGION METROPOLITANA DE SANTIAGO", "provincia": "Santiago", "totalapellido": 1, "totalcomuna": 340282, "prct_apellido": 0.0003, "freq_prov": 0.017023, "freq_reg": 0.018986, "cod_comuna": "13101"}]}, "kvesada": {"apellido": "KVESADA", "comunas": [{"comuna": "HUECHURABA", "region": "13. REGION METROPOLITANA DE SANTIAGO", "provincia": "Santiago", "totalapellido": 1, "totalcomuna": 73498, "prct_apellido": 0.0014, "freq_prov": 0.017023, "freq_reg": 0.018986, "cod_comuna": "13107"}]}, "kveton": {"apellido": "KVETON", "comunas": [{"comuna": "VIÑA DEL MAR", "region": "05. REGION DE VALPARAISO", "provincia": "Valparaíso", "totalapellido": 2, "totalcomuna": 301370, "prct_apellido": 0.0007, "freq_prov": 0.017698, "freq_reg": 0.029341, "cod_comuna": "05109"}]}, "kviatkovskaia": {"apellido": "KVIATKOVSKAIA", "comunas": [{"comuna": "VIÑA DEL MAR", "region": "05. REGION DE VALPARAISO", "provincia": "Valparaíso", "totalapellido": 1, "totalcomuna": 301370, "prct_apellido": 0.0003, "freq_prov": 0.017698, "freq_reg": 0.029341, "cod_comuna": "05109"}]}, "kvich": {"apellido": "KVICH", "comunas": [{"comuna": "LAS CONDES", "region": "13. REGION METROPOLITANA DE SANTIAGO", "provincia": "Santiago", "totalapellido": 1, "totalcomuna": 269517, "prct_apellido": 0.0004, "freq_prov": 0.017023, "freq_reg": 0.018986, "cod_comuna": "13114"}]}, "kvyatkovskaya": {"apellido": "KVYATKOVSKAYA", "comunas": [{"comuna": "VALPARAISO", "region": "05. REGION DE VALPARAISO", "provincia": "Valparaíso", "totalapellido": 1, "totalcomuna": 290125, "prct_apellido": 0.0003, "freq_prov": 0.017698, "freq_reg": 0.029341, "cod_comuna": "05101"}]}}