{"om": {"apellido": "OM", "comunas": [{"comuna": "RECOLETA", "region": "13. REGION METROPOLITANA DE SANTIAGO", "provincia": "Santiago", "totalapellido": 2, "totalcomuna": 142696, "prct_apellido": 1.4e-05, "freq_prov": 0.017023, "freq_reg": 0.018986, "cod_comuna": "13127"}, {"comuna": "PROVIDENCIA", "region": "13. REGION METROPOLITANA DE SANTIAGO", "provincia": "Santiago", "totalapellido": 1, "totalcomuna": 170255, "prct_apellido": 6e-06, "freq_prov": 0.017023, "freq_reg": 0.018986, "cod_comuna": "13123"}]}, "omador": {"apellido": "OMADOR", "comunas": [{"comuna": "PADRE LAS CASAS", "region": "09. REGION DE LA ARAUCANIA", "provincia": "Cautín", "totalapellido": 9, "totalcomuna": 58858, "prct_apellido": 0.000153, "freq_prov": 0.043946, "freq_reg": 0.051873, "cod_comuna": "09112"}]}, "omans": {"apellido": "OMANS", "comunas": [{"comuna": "FUTRONO", "region": "14. REGION DE LOS RIOS", "provincia": "Ranco", "totalapellido": 1, "totalcomuna": 14637, "prct_apellido": 6.8e-05, "freq_prov": 0.112447, "freq_reg": 0.0544, "cod_comuna": "14202"}, {"comuna": "VALDIVIA", "region": "14. REGION DE LOS RIOS", "provincia": "Valdivia", "totalapellido": 3, "totalcomuna": 138619, "prct_apellido": 2.2e-05, "freq_prov": 0.046113, "freq_reg": 0.0544, "cod_comuna": "14101"}]}, "omar": {"apellido": "OMAR", "comunas": [{"comuna": "CALERA", "region": "05. REGION DE VALPARAISO", "provincia": "Quillota", "totalapellido": 45, "totalcomuna": 44980, "prct_apellido": 0.001, "freq_prov": 0.079787, "freq_reg": 0.029341, "cod_comuna": "05502"}, {"comuna": "LA CRUZ", "region": "05. REGION DE VALPARAISO", "provincia": "Quillota", "totalapellido": 2, "totalcomuna": 16329, "prct_apellido": 0.000122, "freq_prov": 0.079787, "freq_reg": 0.029341, "cod_comuna": "05504"}, {"comuna": "LOS VILOS", "region": "04. REGION DE COQUIMBO", "provincia": "Choapa", "totalapellido": 2, "totalcomuna": 18266, "prct_apellido": 0.000109, "freq_prov": 0.165554, "freq_reg": 0.046565, "cod_comuna": "04203"}, {"comuna": "LA UNION", "region": "14. REGION DE LOS RIOS", "provincia": "Ranco", "totalapellido": 1, "totalcomuna": 35754, "prct_apellido": 2.8e-05, "freq_prov": 0.112447, "freq_reg": 0.0544, "cod_comuna": "14201"}, {"comuna": "PEÑALOLEN", "region": "13. REGION METROPOLITANA DE SANTIAGO", "provincia": "Santiago", "totalapellido": 3, "totalcomuna": 191707, "prct_apellido": 1.6e-05, "freq_prov": 0.017023, "freq_reg": 0.018986, "cod_comuna": "13122"}, {"comuna": "LAS CONDES", "region": "13. REGION METROPOLITANA DE SANTIAGO", "provincia": "Santiago", "totalapellido": 14, "totalcomuna": 269517, "prct_apellido": 5.2e-05, "freq_prov": 0.017023, "freq_reg": 0.018986, "cod_comuna": "13114"}, {"comuna": "VALDIVIA", "region": "14. REGION DE LOS RIOS", "provincia": "Valdivia", "totalapellido": 2, "totalcomuna": 138619, "prct_apellido": 1.4e-05, "freq_prov": 0.046113, "freq_reg": 0.0544, "cod_comuna": "14101"}, {"comuna": "ÑUÑOA", "region": "13. REGION METROPOLITANA DE SANTIAGO", "provincia": "Santiago", "totalapellido": 5, "totalcomuna": 197198, "prct_apellido": 2.5e-05, "freq_prov": 0.017023, "freq_reg": 0.018986, "cod_comuna": "13120"}, {"comuna": "LA FLORIDA", "region": "13. REGION METROPOLITANA DE SANTIAGO", "provincia": "Santiago", "totalapellido": 5, "totalcomuna": 307414, "prct_apellido": 1.6e-05, "freq_prov": 0.017023, "freq_reg": 0.018986, "cod_comuna": "13110"}]}, "omatoi": {"apellido": "OMATOI", "comunas": [{"comuna": "LO BARNECHEA", "region": "13. REGION METROPOLITANA DE SANTIAGO", "provincia": "Santiago", "totalapellido": 1, "totalcomuna": 82669, "prct_apellido": 1.2e-05, "freq_prov": 0.017023, "freq_reg": 0.018986, "cod_comuna": "13115"}, {"comuna": "LAS CONDES", "region": "13. REGION METROPOLITANA DE SANTIAGO", "provincia": "Santiago", "totalapellido": 3, "totalcomuna": 269517, "prct_apellido": 1.1e-05, "freq_prov": 0.017023, "freq_reg": 0.018986, "cod_comuna": "13114"}]}, "ombler": {"apellido": "OMBLER", "comunas": [{"comuna": "COLINA", "region": "13. REGION METROPOLITANA DE SANTIAGO", "provincia": "Chacabuco", "totalapellido": 1, "totalcomuna": 90446, "prct_apellido": 1.1e-05, "freq_prov": 0.035407, "freq_reg": 0.018986, "cod_comuna": "13301"}]}, "omegna": {"apellido": "OMEGNA", "comunas": [{"comuna": "MOSTAZAL", "region": "06. REGION DEL LIBERTADOR GENERAL BERNARDO O'HIGGINS", "provincia": "Cachapoal", "totalapellido": 7, "totalcomuna": 20983, "prct_apellido": 0.000334, "freq_prov": 0.061427, "freq_reg": 0.074338, "cod_comuna": "06110"}, {"comuna": "CARAHUE", "region": "09. REGION DE LA ARAUCANIA", "provincia": "Cautín", "totalapellido": 3, "totalcomuna": 24697, "prct_apellido": 0.000121, "freq_prov": 0.043946, "freq_reg": 0.051873, "cod_comuna": "09102"}, {"comuna": "CONCON", "region": "05. REGION DE VALPARAISO", "provincia": "Valparaíso", "totalapellido": 2, "totalcomuna": 39439, "prct_apellido": 5.1e-05, "freq_prov": 0.017698, "freq_reg": 0.029341, "cod_comuna": "05103"}, {"comuna": "LAMPA", "region": "13. REGION METROPOLITANA DE SANTIAGO", "provincia": "Chacabuco", "totalapellido": 3, "totalcomuna": 59623, "prct_apellido": 5e-05, "freq_prov": 0.035407, "freq_reg": 0.018986, "cod_comuna": "13302"}, {"comuna": "ISLA DE MAIPO", "region": "13. REGION METROPOLITANA DE SANTIAGO", "provincia": "Talagante", "totalapellido": 1, "totalcomuna": 27965, "prct_apellido": 3.6e-05, "freq_prov": 0.065142, "freq_reg": 0.018986, "cod_comuna": "13603"}, {"comuna": "LAS CONDES", "region": "13. REGION METROPOLITANA DE SANTIAGO", "provincia": "Santiago", "totalapellido": 10, "totalcomuna": 269517, "prct_apellido": 3.7e-05, "freq_prov": 0.017023, "freq_reg": 0.018986, "cod_comuna": "13114"}, {"comuna": "LA REINA", "region": "13. REGION METROPOLITANA DE SANTIAGO", "provincia": "Santiago", "totalapellido": 4, "totalcomuna": 91556, "prct_apellido": 4.4e-05, "freq_prov": 0.017023, "freq_reg": 0.018986, "cod_comuna": "13113"}, {"comuna": "ANGOL", "region": "09. REGION DE LA ARAUCANIA", "provincia": "Malleco", "totalapellido": 1, "totalcomuna": 47137, "prct_apellido": 2.1e-05, "freq_prov": 0.133465, "freq_reg": 0.051873, "cod_comuna": "09201"}, {"comuna": "TEMUCO", "region": "09. REGION DE LA ARAUCANIA", "provincia": "Cautín", "totalapellido": 6, "totalcomuna": 236909, "prct_apellido": 2.5e-05, "freq_prov": 0.043946, "freq_reg": 0.051873, "cod_comuna": "09101"}, {"comuna": "ÑUÑOA", "region": "13. REGION METROPOLITANA DE SANTIAGO", "provincia": "Santiago", "totalapellido": 15, "totalcomuna": 197198, "prct_apellido": 7.6e-05, "freq_prov": 0.017023, "freq_reg": 0.018986, "cod_comuna": "13120"}, {"comuna": "TALCA", "region": "07. REGION DEL MAULE", "provincia": "Talca", "totalapellido": 2, "totalcomuna": 179640, "prct_apellido": 1.1e-05, "freq_prov": 0.062885, "freq_reg": 0.082553, "cod_comuna": "07101"}, {"comuna": "COLINA", "region": "13. REGION METROPOLITANA DE SANTIAGO", "provincia": "Chacabuco", "totalapellido": 4, "totalcomuna": 90446, "prct_apellido": 4.4e-05, "freq_prov": 0.035407, "freq_reg": 0.018986, "cod_comuna": "13301"}, {"comuna": "MAIPU", "region": "13. REGION METROPOLITANA DE SANTIAGO", "provincia": "Santiago", "totalapellido": 6, "totalcomuna": 389758, "prct_apellido": 1.5e-05, "freq_prov": 0.017023, "freq_reg": 0.018986, "cod_comuna": "13119"}, {"comuna": "VIÑA DEL MAR", "region": "05. REGION DE VALPARAISO", "provincia": "Valparaíso", "totalapellido": 3, "totalcomuna": 301370, "prct_apellido": 1e-05, "freq_prov": 0.017698, "freq_reg": 0.029341, "cod_comuna": "05109"}, {"comuna": "MACUL", "region": "13. REGION METROPOLITANA DE SANTIAGO", "provincia": "Santiago", "totalapellido": 1, "totalcomuna": 101340, "prct_apellido": 1e-05, "freq_prov": 0.017023, "freq_reg": 0.018986, "cod_comuna": "13118"}, {"comuna": "QUINTA NORMAL", "region": "13. REGION METROPOLITANA DE SANTIAGO", "provincia": "Santiago", "totalapellido": 3, "totalcomuna": 102529, "prct_apellido": 2.9e-05, "freq_prov": 0.017023, "freq_reg": 0.018986, "cod_comuna": "13126"}, {"comuna": "EL BOSQUE", "region": "13. REGION METROPOLITANA DE SANTIAGO", "provincia": "Santiago", "totalapellido": 1, "totalcomuna": 137677, "prct_apellido": 7e-06, "freq_prov": 0.017023, "freq_reg": 0.018986, "cod_comuna": "13105"}, {"comuna": "VALDIVIA", "region": "14. REGION DE LOS RIOS", "provincia": "Valdivia", "totalapellido": 1, "totalcomuna": 138619, "prct_apellido": 7e-06, "freq_prov": 0.046113, "freq_reg": 0.0544, "cod_comuna": "14101"}, {"comuna": "PROVIDENCIA", "region": "13. REGION METROPOLITANA DE SANTIAGO", "provincia": "Santiago", "totalapellido": 4, "totalcomuna": 170255, "prct_apellido": 2.3e-05, "freq_prov": 0.017023, "freq_reg": 0.018986, "cod_comuna": "13123"}, {"comuna": "SANTIAGO", "region": "13. REGION METROPOLITANA DE SANTIAGO", "provincia": "Santiago", "totalapellido": 1, "totalcomuna": 340282, "prct_apellido": 3e-06, "freq_prov": 0.017023, "freq_reg": 0.018986, "cod_comuna": "13101"}]}, "omenaca": {"apellido": "OMEÑACA", "comunas": [{"comuna": "TOCOPILLA", "region": "02. REGION DE ANTOFAGASTA", "provincia": "Tocopilla", "totalapellido": 15, "totalcomuna": 22335, "prct_apellido": 0.000672, "freq_prov": 0.11764, "freq_reg": 0.025007, "cod_comuna": "02301"}, {"comuna": "PUMANQUE", "region": "06. REGION DEL LIBERTADOR GENERAL BERNARDO O'HIGGINS", "provincia": "Colchagua", "totalapellido": 1, "totalcomuna": 4333, "prct_apellido": 0.000231, "freq_prov": 0.12967, "freq_reg": 0.074338, "cod_comuna": "06309"}, {"comuna": "LOS ANDES", "region": "05. REGION DE VALPARAISO", "provincia": "Los Andes", "totalapellido": 18, "totalcomuna": 55969, "prct_apellido": 0.000322, "freq_prov": 0.083664, "freq_reg": 0.029341, "cod_comuna": "05301"}, {"comuna": "ROMERAL", "region": "07. REGION DEL MAULE", "provincia": "Curicó", "totalapellido": 1, "totalcomuna": 13823, "prct_apellido": 7.2e-05, "freq_prov": 0.081137, "freq_reg": 0.082553, "cod_comuna": "07306"}, {"comuna": "SAN RAMON", "region": "13. REGION METROPOLITANA DE SANTIAGO", "provincia": "Santiago", "totalapellido": 10, "totalcomuna": 81793, "prct_apellido": 0.000122, "freq_prov": 0.017023, "freq_reg": 0.018986, "cod_comuna": "13131"}, {"comuna": "COLLIPULLI", "region": "09. REGION DE LA ARAUCANIA", "provincia": "Malleco", "totalapellido": 1, "totalcomuna": 22160, "prct_apellido": 4.5e-05, "freq_prov": 0.133465, "freq_reg": 0.051873, "cod_comuna": "09202"}, {"comuna": "ILLAPEL", "region": "04. REGION DE COQUIMBO", "provincia": "Choapa", "totalapellido": 2, "totalcomuna": 27921, "prct_apellido": 7.2e-05, "freq_prov": 0.165554, "freq_reg": 0.046565, "cod_comuna": "04201"}, {"comuna": "LA GRANJA", "region": "13. REGION METROPOLITANA DE SANTIAGO", "provincia": "Santiago", "totalapellido": 3, "totalcomuna": 103905, "prct_apellido": 2.9e-05, "freq_prov": 0.017023, "freq_reg": 0.018986, "cod_comuna": "13111"}, {"comuna": "SAN MIGUEL", "region": "13. REGION METROPOLITANA DE SANTIAGO", "provincia": "Santiago", "totalapellido": 4, "totalcomuna": 105090, "prct_apellido": 3.8e-05, "freq_prov": 0.017023, "freq_reg": 0.018986, "cod_comuna": "13130"}, {"comuna": "MACUL", "region": "13. REGION METROPOLITANA DE SANTIAGO", "provincia": "Santiago", "totalapellido": 2, "totalcomuna": 101340, "prct_apellido": 2e-05, "freq_prov": 0.017023, "freq_reg": 0.018986, "cod_comuna": "13118"}, {"comuna": "TALAGANTE", "region": "13. REGION METROPOLITANA DE SANTIAGO", "provincia": "Talagante", "totalapellido": 1, "totalcomuna": 58141, "prct_apellido": 1.7e-05, "freq_prov": 0.065142, "freq_reg": 0.018986, "cod_comuna": "13601"}, {"comuna": "RECOLETA", "region": "13. REGION METROPOLITANA DE SANTIAGO", "provincia": "Santiago", "totalapellido": 2, "totalcomuna": 142696, "prct_apellido": 1.4e-05, "freq_prov": 0.017023, "freq_reg": 0.018986, "cod_comuna": "13127"}, {"comuna": "BUIN", "region": "13. REGION METROPOLITANA DE SANTIAGO", "provincia": "Maipo", "totalapellido": 1, "totalcomuna": 75333, "prct_apellido": 1.3e-05, "freq_prov": 0.033289, "freq_reg": 0.018986, "cod_comuna": "13402"}, {"comuna": "SAN JOAQUIN", "region": "13. REGION METROPOLITANA DE SANTIAGO", "provincia": "Santiago", "totalapellido": 2, "totalcomuna": 82325, "prct_apellido": 2.4e-05, "freq_prov": 0.017023, "freq_reg": 0.018986, "cod_comuna": "13129"}, {"comuna": "LO BARNECHEA", "region": "13. REGION METROPOLITANA DE SANTIAGO", "provincia": "Santiago", "totalapellido": 1, "totalcomuna": 82669, "prct_apellido": 1.2e-05, "freq_prov": 0.017023, "freq_reg": 0.018986, "cod_comuna": "13115"}, {"comuna": "LA CISTERNA", "region": "13. REGION METROPOLITANA DE SANTIAGO", "provincia": "Santiago", "totalapellido": 2, "totalcomuna": 83246, "prct_apellido": 2.4e-05, "freq_prov": 0.017023, "freq_reg": 0.018986, "cod_comuna": "13109"}, {"comuna": "VITACURA", "region": "13. REGION METROPOLITANA DE SANTIAGO", "provincia": "Santiago", "totalapellido": 1, "totalcomuna": 89311, "prct_apellido": 1.1e-05, "freq_prov": 0.017023, "freq_reg": 0.018986, "cod_comuna": "13132"}, {"comuna": "LA REINA", "region": "13. REGION METROPOLITANA DE SANTIAGO", "provincia": "Santiago", "totalapellido": 3, "totalcomuna": 91556, "prct_apellido": 3.3e-05, "freq_prov": 0.017023, "freq_reg": 0.018986, "cod_comuna": "13113"}, {"comuna": "CALAMA", "region": "02. REGION DE ANTOFAGASTA", "provincia": "El Loa", "totalapellido": 6, "totalcomuna": 132333, "prct_apellido": 4.5e-05, "freq_prov": 0.035053, "freq_reg": 0.025007, "cod_comuna": "02201"}, {"comuna": "QUILPUE", "region": "05. REGION DE VALPARAISO", "provincia": "Marga Marga", "totalapellido": 4, "totalcomuna": 134448, "prct_apellido": 3e-05, "freq_prov": 0.034753, "freq_reg": 0.029341, "cod_comuna": "05801"}, {"comuna": "LAS CONDES", "region": "13. REGION METROPOLITANA DE SANTIAGO", "provincia": "Santiago", "totalapellido": 2, "totalcomuna": 269517, "prct_apellido": 7e-06, "freq_prov": 0.017023, "freq_reg": 0.018986, "cod_comuna": "13114"}, {"comuna": "PROVIDENCIA", "region": "13. REGION METROPOLITANA DE SANTIAGO", "provincia": "Santiago", "totalapellido": 1, "totalcomuna": 170255, "prct_apellido": 6e-06, "freq_prov": 0.017023, "freq_reg": 0.018986, "cod_comuna": "13123"}, {"comuna": "PUENTE ALTO", "region": "13. REGION METROPOLITANA DE SANTIAGO", "provincia": "Cordillera", "totalapellido": 4, "totalcomuna": 399739, "prct_apellido": 1e-05, "freq_prov": 0.019022, "freq_reg": 0.018986, "cod_comuna": "13201"}, {"comuna": "ANTOFAGASTA", "region": "02. REGION DE ANTOFAGASTA", "provincia": "Antofagasta", "totalapellido": 1, "totalcomuna": 286950, "prct_apellido": 3e-06, "freq_prov": 0.020817, "freq_reg": 0.025007, "cod_comuna": "02101"}, {"comuna": "LA FLORIDA", "region": "13. REGION METROPOLITANA DE SANTIAGO", "provincia": "Santiago", "totalapellido": 1, "totalcomuna": 307414, "prct_apellido": 3e-06, "freq_prov": 0.017023, "freq_reg": 0.018986, "cod_comuna": "13110"}]}, "omerovic": {"apellido": "OMEROVIC", "comunas": [{"comuna": "FLORIDA", "region": "08. REGION DEL BIOBIO", "provincia": "Concepción", "totalapellido": 1, "totalcomuna": 10451, "prct_apellido": 9.6e-05, "freq_prov": 0.045559, "freq_reg": 0.056049, "cod_comuna": "08104"}, {"comuna": "VITACURA", "region": "13. REGION METROPOLITANA DE SANTIAGO", "provincia": "Santiago", "totalapellido": 8, "totalcomuna": 89311, "prct_apellido": 9e-05, "freq_prov": 0.017023, "freq_reg": 0.018986, "cod_comuna": "13132"}, {"comuna": "PROVIDENCIA", "region": "13. REGION METROPOLITANA DE SANTIAGO", "provincia": "Santiago", "totalapellido": 8, "totalcomuna": 170255, "prct_apellido": 4.7e-05, "freq_prov": 0.017023, "freq_reg": 0.018986, "cod_comuna": "13123"}, {"comuna": "ANTOFAGASTA", "region": "02. REGION DE ANTOFAGASTA", "provincia": "Antofagasta", "totalapellido": 5, "totalcomuna": 286950, "prct_apellido": 1.7e-05, "freq_prov": 0.020817, "freq_reg": 0.025007, "cod_comuna": "02101"}, {"comuna": "LO BARNECHEA", "region": "13. REGION METROPOLITANA DE SANTIAGO", "provincia": "Santiago", "totalapellido": 3, "totalcomuna": 82669, "prct_apellido": 3.6e-05, "freq_prov": 0.017023, "freq_reg": 0.018986, "cod_comuna": "13115"}, {"comuna": "SAN PEDRO DE LA PAZ", "region": "08. REGION DEL BIOBIO", "provincia": "Concepción", "totalapellido": 1, "totalcomuna": 89479, "prct_apellido": 1.1e-05, "freq_prov": 0.045559, "freq_reg": 0.056049, "cod_comuna": "08108"}, {"comuna": "CALAMA", "region": "02. REGION DE ANTOFAGASTA", "provincia": "El Loa", "totalapellido": 6, "totalcomuna": 132333, "prct_apellido": 4.5e-05, "freq_prov": 0.035053, "freq_reg": 0.025007, "cod_comuna": "02201"}, {"comuna": "VALDIVIA", "region": "14. REGION DE LOS RIOS", "provincia": "Valdivia", "totalapellido": 1, "totalcomuna": 138619, "prct_apellido": 7e-06, "freq_prov": 0.046113, "freq_reg": 0.0544, "cod_comuna": "14101"}, {"comuna": "SANTIAGO", "region": "13. REGION METROPOLITANA DE SANTIAGO", "provincia": "Santiago", "totalapellido": 2, "totalcomuna": 340282, "prct_apellido": 6e-06, "freq_prov": 0.017023, "freq_reg": 0.018986, "cod_comuna": "13101"}, {"comuna": "LA SERENA", "region": "04. REGION DE COQUIMBO", "provincia": "Elqui", "totalapellido": 3, "totalcomuna": 174853, "prct_apellido": 1.7e-05, "freq_prov": 0.034381, "freq_reg": 0.046565, "cod_comuna": "04101"}, {"comuna": "CONCEPCION", "region": "08. REGION DEL BIOBIO", "provincia": "Concepción", "totalapellido": 1, "totalcomuna": 201066, "prct_apellido": 5e-06, "freq_prov": 0.045559, "freq_reg": 0.056049, "cod_comuna": "08101"}]}, "omerovich": {"apellido": "OMEROVICH", "comunas": [{"comuna": "LA GRANJA", "region": "13. REGION METROPOLITANA DE SANTIAGO", "provincia": "Santiago", "totalapellido": 16, "totalcomuna": 103905, "prct_apellido": 0.000154, "freq_prov": 0.017023, "freq_reg": 0.018986, "cod_comuna": "13111"}, {"comuna": "LA FLORIDA", "region": "13. REGION METROPOLITANA DE SANTIAGO", "provincia": "Santiago", "totalapellido": 12, "totalcomuna": 307414, "prct_apellido": 3.9e-05, "freq_prov": 0.017023, "freq_reg": 0.018986, "cod_comuna": "13110"}, {"comuna": "CERRILLOS", "region": "13. REGION METROPOLITANA DE SANTIAGO", "provincia": "Santiago", "totalapellido": 1, "totalcomuna": 67537, "prct_apellido": 1.5e-05, "freq_prov": 0.017023, "freq_reg": 0.018986, "cod_comuna": "13102"}, {"comuna": "PUENTE ALTO", "region": "13. REGION METROPOLITANA DE SANTIAGO", "provincia": "Cordillera", "totalapellido": 10, "totalcomuna": 399739, "prct_apellido": 2.5e-05, "freq_prov": 0.019022, "freq_reg": 0.018986, "cod_comuna": "13201"}, {"comuna": "COPIAPO", "region": "03. REGION DE ATACAMA", "provincia": "Copiapó", "totalapellido": 3, "totalcomuna": 123973, "prct_apellido": 2.4e-05, "freq_prov": 0.043922, "freq_reg": 0.058317, "cod_comuna": "03101"}, {"comuna": "VALDIVIA", "region": "14. REGION DE LOS RIOS", "provincia": "Valdivia", "totalapellido": 1, "totalcomuna": 138619, "prct_apellido": 7e-06, "freq_prov": 0.046113, "freq_reg": 0.0544, "cod_comuna": "14101"}, {"comuna": "RECOLETA", "region": "13. REGION METROPOLITANA DE SANTIAGO", "provincia": "Santiago", "totalapellido": 1, "totalcomuna": 142696, "prct_apellido": 7e-06, "freq_prov": 0.017023, "freq_reg": 0.018986, "cod_comuna": "13127"}, {"comuna": "SANTIAGO", "region": "13. REGION METROPOLITANA DE SANTIAGO", "provincia": "Santiago", "totalapellido": 6, "totalcomuna": 340282, "prct_apellido": 1.8e-05, "freq_prov": 0.017023, "freq_reg": 0.018986, "cod_comuna": "13101"}, {"comuna": "ÑUÑOA", "region": "13. REGION METROPOLITANA DE SANTIAGO", "provincia": "Santiago", "totalapellido": 1, "totalcomuna": 197198, "prct_apellido": 5e-06, "freq_prov": 0.017023, "freq_reg": 0.018986, "cod_comuna": "13120"}]}, "ominami": {"apellido": "OMINAMI", "comunas": [{"comuna": "ZAPALLAR", "region": "05. REGION DE VALPARAISO", "provincia": "Petorca", "totalapellido": 1, "totalcomuna": 8709, "prct_apellido": 0.000115, "freq_prov": 0.160073, "freq_reg": 0.029341, "cod_comuna": "05405"}, {"comuna": "PROVIDENCIA", "region": "13. REGION METROPOLITANA DE SANTIAGO", "provincia": "Santiago", "totalapellido": 2, "totalcomuna": 170255, "prct_apellido": 1.2e-05, "freq_prov": 0.017023, "freq_reg": 0.018986, "cod_comuna": "13123"}]}, "ominetti": {"apellido": "OMINETTI", "comunas": [{"comuna": "VIÑA DEL MAR", "region": "05. REGION DE VALPARAISO", "provincia": "Valparaíso", "totalapellido": 2, "totalcomuna": 301370, "prct_apellido": 7e-06, "freq_prov": 0.017698, "freq_reg": 0.029341, "cod_comuna": "05109"}]}, "omke": {"apellido": "OMKE", "comunas": [{"comuna": "CONCHALI", "region": "13. REGION METROPOLITANA DE SANTIAGO", "provincia": "Santiago", "totalapellido": 1, "totalcomuna": 118624, "prct_apellido": 8e-06, "freq_prov": 0.017023, "freq_reg": 0.018986, "cod_comuna": "13104"}, {"comuna": "QUILICURA", "region": "13. REGION METROPOLITANA DE SANTIAGO", "provincia": "Santiago", "totalapellido": 4, "totalcomuna": 139914, "prct_apellido": 2.9e-05, "freq_prov": 0.017023, "freq_reg": 0.018986, "cod_comuna": "13125"}, {"comuna": "PUENTE ALTO", "region": "13. REGION METROPOLITANA DE SANTIAGO", "provincia": "Cordillera", "totalapellido": 2, "totalcomuna": 399739, "prct_apellido": 5e-06, "freq_prov": 0.019022, "freq_reg": 0.018986, "cod_comuna": "13201"}]}, "ommidvar": {"apellido": "OMMIDVAR", "comunas": [{"comuna": "SANTA CRUZ", "region": "06. REGION DEL LIBERTADOR GENERAL BERNARDO O'HIGGINS", "provincia": "Colchagua", "totalapellido": 1, "totalcomuna": 31217, "prct_apellido": 3.2e-05, "freq_prov": 0.12967, "freq_reg": 0.074338, "cod_comuna": "06310"}, {"comuna": "LO BARNECHEA", "region": "13. REGION METROPOLITANA DE SANTIAGO", "provincia": "Santiago", "totalapellido": 2, "totalcomuna": 82669, "prct_apellido": 2.4e-05, "freq_prov": 0.017023, "freq_reg": 0.018986, "cod_comuna": "13115"}, {"comuna": "PROVIDENCIA", "region": "13. REGION METROPOLITANA DE SANTIAGO", "provincia": "Santiago", "totalapellido": 2, "totalcomuna": 170255, "prct_apellido": 1.2e-05, "freq_prov": 0.017023, "freq_reg": 0.018986, "cod_comuna": "13123"}, {"comuna": "LA GRANJA", "region": "13. REGION METROPOLITANA DE SANTIAGO", "provincia": "Santiago", "totalapellido": 1, "totalcomuna": 103905, "prct_apellido": 1e-05, "freq_prov": 0.017023, "freq_reg": 0.018986, "cod_comuna": "13111"}, {"comuna": "LA FLORIDA", "region": "13. REGION METROPOLITANA DE SANTIAGO", "provincia": "Santiago", "totalapellido": 1, "totalcomuna": 307414, "prct_apellido": 3e-06, "freq_prov": 0.017023, "freq_reg": 0.018986, "cod_comuna": "13110"}]}, "omnes": {"apellido": "OMNES", "comunas": [{"comuna": "CONCEPCION", "region": "08. REGION DEL BIOBIO", "provincia": "Concepción", "totalapellido": 1, "totalcomuna": 201066, "prct_apellido": 5e-06, "freq_prov": 0.045559, "freq_reg": 0.056049, "cod_comuna": "08101"}]}, "omoboni": {"apellido": "OMOBONI", "comunas": [{"comuna": "QUILPUE", "region": "05. REGION DE VALPARAISO", "provincia": "Marga Marga", "totalapellido": 3, "totalcomuna": 134448, "prct_apellido": 2.2e-05, "freq_prov": 0.034753, "freq_reg": 0.029341, "cod_comuna": "05801"}, {"comuna": "ANTOFAGASTA", "region": "02. REGION DE ANTOFAGASTA", "provincia": "Antofagasta", "totalapellido": 2, "totalcomuna": 286950, "prct_apellido": 7e-06, "freq_prov": 0.020817, "freq_reg": 0.025007, "cod_comuna": "02101"}, {"comuna": "LAS CONDES", "region": "13. REGION METROPOLITANA DE SANTIAGO", "provincia": "Santiago", "totalapellido": 2, "totalcomuna": 269517, "prct_apellido": 7e-06, "freq_prov": 0.017023, "freq_reg": 0.018986, "cod_comuna": "13114"}, {"comuna": "VIÑA DEL MAR", "region": "05. REGION DE VALPARAISO", "provincia": "Valparaíso", "totalapellido": 1, "totalcomuna": 301370, "prct_apellido": 3e-06, "freq_prov": 0.017698, "freq_reg": 0.029341, "cod_comuna": "05109"}]}, "omodei": {"apellido": "OMODEI", "comunas": [{"comuna": "COIHAIQUE", "region": "11. REGION DE AYSEN DEL GENERAL CARLOS IBAÑEZ DEL CAMPO", "provincia": NaN, "totalapellido": 2, "totalcomuna": 54229, "prct_apellido": 3.7e-05, "freq_prov": NaN, "freq_reg": 0.077233}]}, "omomo": {"apellido": "OMOMO", "comunas": [{"comuna": "LAS CONDES", "region": "13. REGION METROPOLITANA DE SANTIAGO", "provincia": "Santiago", "totalapellido": 1, "totalcomuna": 269517, "prct_apellido": 4e-06, "freq_prov": 0.017023, "freq_reg": 0.018986, "cod_comuna": "13114"}]}, "omon": {"apellido": "OMON", "comunas": [{"comuna": "NATALES", "region": "12. REGION DE MAGALLANES Y DE LA ANTARTICA CHILENA", "provincia": "Última Esperanza", "totalapellido": 1, "totalcomuna": 22709, "prct_apellido": 4.4e-05, "freq_prov": 0.096903, "freq_reg": 0.037004, "cod_comuna": "12401"}, {"comuna": "HUECHURABA", "region": "13. REGION METROPOLITANA DE SANTIAGO", "provincia": "Santiago", "totalapellido": 2, "totalcomuna": 73498, "prct_apellido": 2.7e-05, "freq_prov": 0.017023, "freq_reg": 0.018986, "cod_comuna": "13107"}, {"comuna": "COPIAPO", "region": "03. REGION DE ATACAMA", "provincia": "Copiapó", "totalapellido": 3, "totalcomuna": 123973, "prct_apellido": 2.4e-05, "freq_prov": 0.043922, "freq_reg": 0.058317, "cod_comuna": "03101"}, {"comuna": "CALERA", "region": "05. REGION DE VALPARAISO", "provincia": "Quillota", "totalapellido": 1, "totalcomuna": 44980, "prct_apellido": 2.2e-05, "freq_prov": 0.079787, "freq_reg": 0.029341, "cod_comuna": "05502"}, {"comuna": "LOS ANGELES", "region": "08. REGION DEL BIOBIO", "provincia": "Biobío", "totalapellido": 2, "totalcomuna": 162845, "prct_apellido": 1.2e-05, "freq_prov": 0.077416, "freq_reg": 0.056049, "cod_comuna": "08301"}, {"comuna": "COQUIMBO", "region": "04. REGION DE COQUIMBO", "provincia": "Elqui", "totalapellido": 2, "totalcomuna": 167854, "prct_apellido": 1.2e-05, "freq_prov": 0.034381, "freq_reg": 0.046565, "cod_comuna": "04102"}, {"comuna": "SANTIAGO", "region": "13. REGION METROPOLITANA DE SANTIAGO", "provincia": "Santiago", "totalapellido": 5, "totalcomuna": 340282, "prct_apellido": 1.5e-05, "freq_prov": 0.017023, "freq_reg": 0.018986, "cod_comuna": "13101"}, {"comuna": "LO PRADO", "region": "13. REGION METROPOLITANA DE SANTIAGO", "provincia": "Santiago", "totalapellido": 2, "totalcomuna": 88885, "prct_apellido": 2.3e-05, "freq_prov": 0.017023, "freq_reg": 0.018986, "cod_comuna": "13117"}, {"comuna": "OVALLE", "region": "04. REGION DE COQUIMBO", "provincia": "Limarí", "totalapellido": 3, "totalcomuna": 91832, "prct_apellido": 3.3e-05, "freq_prov": 0.102708, "freq_reg": 0.046565, "cod_comuna": "04301"}, {"comuna": "ESTACION CENTRAL", "region": "13. REGION METROPOLITANA DE SANTIAGO", "provincia": "Santiago", "totalapellido": 1, "totalcomuna": 127214, "prct_apellido": 8e-06, "freq_prov": 0.017023, "freq_reg": 0.018986, "cod_comuna": "13106"}, {"comuna": "QUILPUE", "region": "05. REGION DE VALPARAISO", "provincia": "Marga Marga", "totalapellido": 1, "totalcomuna": 134448, "prct_apellido": 7e-06, "freq_prov": 0.034753, "freq_reg": 0.029341, "cod_comuna": "05801"}, {"comuna": "PEÑALOLEN", "region": "13. REGION METROPOLITANA DE SANTIAGO", "provincia": "Santiago", "totalapellido": 1, "totalcomuna": 191707, "prct_apellido": 5e-06, "freq_prov": 0.017023, "freq_reg": 0.018986, "cod_comuna": "13122"}, {"comuna": "RANCAGUA", "region": "06. REGION DEL LIBERTADOR GENERAL BERNARDO O'HIGGINS", "provincia": "Cachapoal", "totalapellido": 2, "totalcomuna": 194487, "prct_apellido": 1e-05, "freq_prov": 0.061427, "freq_reg": 0.074338, "cod_comuna": "06101"}, {"comuna": "ÑUÑOA", "region": "13. REGION METROPOLITANA DE SANTIAGO", "provincia": "Santiago", "totalapellido": 1, "totalcomuna": 197198, "prct_apellido": 5e-06, "freq_prov": 0.017023, "freq_reg": 0.018986, "cod_comuna": "13120"}, {"comuna": "TEMUCO", "region": "09. REGION DE LA ARAUCANIA", "provincia": "Cautín", "totalapellido": 1, "totalcomuna": 236909, "prct_apellido": 4e-06, "freq_prov": 0.043946, "freq_reg": 0.051873, "cod_comuna": "09101"}]}, "omonte": {"apellido": "OMONTE", "comunas": [{"comuna": "ALTO HOSPICIO", "region": "01. REGION DE TARAPACA", "provincia": "Iquique", "totalapellido": 26, "totalcomuna": 58683, "prct_apellido": 0.000443, "freq_prov": 0.023146, "freq_reg": 0.02576, "cod_comuna": "01107"}, {"comuna": "POZO ALMONTE", "region": "01. REGION DE TARAPACA", "provincia": "Tamarugal", "totalapellido": 4, "totalcomuna": 11898, "prct_apellido": 0.000336, "freq_prov": 0.130887, "freq_reg": 0.02576, "cod_comuna": "01401"}, {"comuna": "IQUIQUE", "region": "01. REGION DE TARAPACA", "provincia": "Iquique", "totalapellido": 37, "totalcomuna": 167553, "prct_apellido": 0.000221, "freq_prov": 0.023146, "freq_reg": 0.02576, "cod_comuna": "01101"}, {"comuna": "HUARA", "region": "01. REGION DE TARAPACA", "provincia": "Tamarugal", "totalapellido": 3, "totalcomuna": 9373, "prct_apellido": 0.00032, "freq_prov": 0.130887, "freq_reg": 0.02576, "cod_comuna": "01404"}, {"comuna": "LA FLORIDA", "region": "13. REGION METROPOLITANA DE SANTIAGO", "provincia": "Santiago", "totalapellido": 9, "totalcomuna": 307414, "prct_apellido": 2.9e-05, "freq_prov": 0.017023, "freq_reg": 0.018986, "cod_comuna": "13110"}, {"comuna": "ANTOFAGASTA", "region": "02. REGION DE ANTOFAGASTA", "provincia": "Antofagasta", "totalapellido": 12, "totalcomuna": 286950, "prct_apellido": 4.2e-05, "freq_prov": 0.020817, "freq_reg": 0.025007, "cod_comuna": "02101"}, {"comuna": "SANTIAGO", "region": "13. REGION METROPOLITANA DE SANTIAGO", "provincia": "Santiago", "totalapellido": 7, "totalcomuna": 340282, "prct_apellido": 2.1e-05, "freq_prov": 0.017023, "freq_reg": 0.018986, "cod_comuna": "13101"}, {"comuna": "ARICA", "region": "15. REGION DE ARICA Y PARINACOTA", "provincia": "Arica", "totalapellido": 10, "totalcomuna": 180060, "prct_apellido": 5.6e-05, "freq_prov": 0.025797, "freq_reg": 0.026725, "cod_comuna": "15101"}, {"comuna": "COPIAPO", "region": "03. REGION DE ATACAMA", "provincia": "Copiapó", "totalapellido": 9, "totalcomuna": 123973, "prct_apellido": 7.3e-05, "freq_prov": 0.043922, "freq_reg": 0.058317, "cod_comuna": "03101"}, {"comuna": "CALAMA", "region": "02. REGION DE ANTOFAGASTA", "provincia": "El Loa", "totalapellido": 5, "totalcomuna": 132333, "prct_apellido": 3.8e-05, "freq_prov": 0.035053, "freq_reg": 0.025007, "cod_comuna": "02201"}, {"comuna": "QUILICURA", "region": "13. REGION METROPOLITANA DE SANTIAGO", "provincia": "Santiago", "totalapellido": 2, "totalcomuna": 139914, "prct_apellido": 1.4e-05, "freq_prov": 0.017023, "freq_reg": 0.018986, "cod_comuna": "13125"}, {"comuna": "MAIPU", "region": "13. REGION METROPOLITANA DE SANTIAGO", "provincia": "Santiago", "totalapellido": 10, "totalcomuna": 389758, "prct_apellido": 2.6e-05, "freq_prov": 0.017023, "freq_reg": 0.018986, "cod_comuna": "13119"}, {"comuna": "MACUL", "region": "13. REGION METROPOLITANA DE SANTIAGO", "provincia": "Santiago", "totalapellido": 1, "totalcomuna": 101340, "prct_apellido": 1e-05, "freq_prov": 0.017023, "freq_reg": 0.018986, "cod_comuna": "13118"}, {"comuna": "CERRO NAVIA", "region": "13. REGION METROPOLITANA DE SANTIAGO", "provincia": "Santiago", "totalapellido": 1, "totalcomuna": 115479, "prct_apellido": 9e-06, "freq_prov": 0.017023, "freq_reg": 0.018986, "cod_comuna": "13103"}, {"comuna": "RANCAGUA", "region": "06. REGION DEL LIBERTADOR GENERAL BERNARDO O'HIGGINS", "provincia": "Cachapoal", "totalapellido": 1, "totalcomuna": 194487, "prct_apellido": 5e-06, "freq_prov": 0.061427, "freq_reg": 0.074338, "cod_comuna": "06101"}, {"comuna": "CONCEPCION", "region": "08. REGION DEL BIOBIO", "provincia": "Concepción", "totalapellido": 1, "totalcomuna": 201066, "prct_apellido": 5e-06, "freq_prov": 0.045559, "freq_reg": 0.056049, "cod_comuna": "08101"}, {"comuna": "VALPARAISO", "region": "05. REGION DE VALPARAISO", "provincia": "Valparaíso", "totalapellido": 1, "totalcomuna": 290125, "prct_apellido": 3e-06, "freq_prov": 0.017698, "freq_reg": 0.029341, "cod_comuna": "05101"}, {"comuna": "PUENTE ALTO", "region": "13. REGION METROPOLITANA DE SANTIAGO", "provincia": "Cordillera", "totalapellido": 3, "totalcomuna": 399739, "prct_apellido": 8e-06, "freq_prov": 0.019022, "freq_reg": 0.018986, "cod_comuna": "13201"}]}, "omori": {"apellido": "OMORI", "comunas": [{"comuna": "VALLENAR", "region": "03. REGION DE ATACAMA", "provincia": "Huasco", "totalapellido": 2, "totalcomuna": 45529, "prct_apellido": 4.4e-05, "freq_prov": 0.121458, "freq_reg": 0.058317, "cod_comuna": "03301"}, {"comuna": "VICUÑA", "region": "04. REGION DE COQUIMBO", "provincia": "Elqui", "totalapellido": 1, "totalcomuna": 23678, "prct_apellido": 4.2e-05, "freq_prov": 0.034381, "freq_reg": 0.046565, "cod_comuna": "04106"}, {"comuna": "CONCEPCION", "region": "08. REGION DEL BIOBIO", "provincia": "Concepción", "totalapellido": 2, "totalcomuna": 201066, "prct_apellido": 1e-05, "freq_prov": 0.045559, "freq_reg": 0.056049, "cod_comuna": "08101"}, {"comuna": "COPIAPO", "region": "03. REGION DE ATACAMA", "provincia": "Copiapó", "totalapellido": 1, "totalcomuna": 123973, "prct_apellido": 8e-06, "freq_prov": 0.043922, "freq_reg": 0.058317, "cod_comuna": "03101"}, {"comuna": "SANTIAGO", "region": "13. REGION METROPOLITANA DE SANTIAGO", "provincia": "Santiago", "totalapellido": 1, "totalcomuna": 340282, "prct_apellido": 3e-06, "freq_prov": 0.017023, "freq_reg": 0.018986, "cod_comuna": "13101"}]}, "omote": {"apellido": "OMOTE", "comunas": [{"comuna": "QUINTA NORMAL", "region": "13. REGION METROPOLITANA DE SANTIAGO", "provincia": "Santiago", "totalapellido": 1, "totalcomuna": 102529, "prct_apellido": 1e-05, "freq_prov": 0.017023, "freq_reg": 0.018986, "cod_comuna": "13126"}, {"comuna": "SANTIAGO", "region": "13. REGION METROPOLITANA DE SANTIAGO", "provincia": "Santiago", "totalapellido": 1, "totalcomuna": 340282, "prct_apellido": 3e-06, "freq_prov": 0.017023, "freq_reg": 0.018986, "cod_comuna": "13101"}]}, "oms": {"apellido": "OMS", "comunas": [{"comuna": "LOS VILOS", "region": "04. REGION DE COQUIMBO", "provincia": "Choapa", "totalapellido": 1, "totalcomuna": 18266, "prct_apellido": 5.5e-05, "freq_prov": 0.165554, "freq_reg": 0.046565, "cod_comuna": "04203"}, {"comuna": "LAS CONDES", "region": "13. REGION METROPOLITANA DE SANTIAGO", "provincia": "Santiago", "totalapellido": 1, "totalcomuna": 269517, "prct_apellido": 4e-06, "freq_prov": 0.017023, "freq_reg": 0.018986, "cod_comuna": "13114"}]}}