{"kcacha": {"apellido": "KCACHA", "comunas": [{"comuna": "LAMPA", "region": "13. REGION METROPOLITANA DE SANTIAGO", "provincia": "Chacabuco", "totalapellido": 1, "totalcomuna": 59623, "prct_apellido": 0.0017, "freq_prov": 0.035407, "freq_reg": 0.018986, "cod_comuna": "13302"}, {"comuna": "SANTIAGO", "region": "13. REGION METROPOLITANA DE SANTIAGO", "provincia": "Santiago", "totalapellido": 1, "totalcomuna": 340282, "prct_apellido": 0.0003, "freq_prov": 0.017023, "freq_reg": 0.018986, "cod_comuna": "13101"}]}, "kcomt": {"apellido": "KCOMT", "comunas": [{"comuna": "LAS CONDES", "region": "13. REGION METROPOLITANA DE SANTIAGO", "provincia": "Santiago", "totalapellido": 6, "totalcomuna": 269517, "prct_apellido": 0.0022, "freq_prov": 0.017023, "freq_reg": 0.018986, "cod_comuna": "13114"}]}}