{"ucanan": {"apellido": "UCAÑAN", "comunas": [{"comuna": "INDEPENDENCIA", "region": "13. REGION METROPOLITANA DE SANTIAGO", "provincia": "Santiago", "totalapellido": 4, "totalcomuna": 82629, "prct_apellido": 4.8e-05, "freq_prov": 0.017023, "freq_reg": 0.018986, "cod_comuna": "13108"}, {"comuna": "HUECHURABA", "region": "13. REGION METROPOLITANA DE SANTIAGO", "provincia": "Santiago", "totalapellido": 2, "totalcomuna": 73498, "prct_apellido": 2.7e-05, "freq_prov": 0.017023, "freq_reg": 0.018986, "cod_comuna": "13107"}, {"comuna": "ALTO HOSPICIO", "region": "01. REGION DE TARAPACA", "provincia": "Iquique", "totalapellido": 1, "totalcomuna": 58683, "prct_apellido": 1.7e-05, "freq_prov": 0.023146, "freq_reg": 0.02576, "cod_comuna": "01107"}, {"comuna": "ESTACION CENTRAL", "region": "13. REGION METROPOLITANA DE SANTIAGO", "provincia": "Santiago", "totalapellido": 3, "totalcomuna": 127214, "prct_apellido": 2.4e-05, "freq_prov": 0.017023, "freq_reg": 0.018986, "cod_comuna": "13106"}, {"comuna": "QUILICURA", "region": "13. REGION METROPOLITANA DE SANTIAGO", "provincia": "Santiago", "totalapellido": 1, "totalcomuna": 139914, "prct_apellido": 7e-06, "freq_prov": 0.017023, "freq_reg": 0.018986, "cod_comuna": "13125"}, {"comuna": "RECOLETA", "region": "13. REGION METROPOLITANA DE SANTIAGO", "provincia": "Santiago", "totalapellido": 2, "totalcomuna": 142696, "prct_apellido": 1.4e-05, "freq_prov": 0.017023, "freq_reg": 0.018986, "cod_comuna": "13127"}, {"comuna": "ARICA", "region": "15. REGION DE ARICA Y PARINACOTA", "provincia": "Arica", "totalapellido": 2, "totalcomuna": 180060, "prct_apellido": 1.1e-05, "freq_prov": 0.025797, "freq_reg": 0.026725, "cod_comuna": "15101"}, {"comuna": "ANTOFAGASTA", "region": "02. REGION DE ANTOFAGASTA", "provincia": "Antofagasta", "totalapellido": 5, "totalcomuna": 286950, "prct_apellido": 1.7e-05, "freq_prov": 0.020817, "freq_reg": 0.025007, "cod_comuna": "02101"}, {"comuna": "SANTIAGO", "region": "13. REGION METROPOLITANA DE SANTIAGO", "provincia": "Santiago", "totalapellido": 4, "totalcomuna": 340282, "prct_apellido": 1.2e-05, "freq_prov": 0.017023, "freq_reg": 0.018986, "cod_comuna": "13101"}]}, "ucanay": {"apellido": "UCAÑAY", "comunas": [{"comuna": "RECOLETA", "region": "13. REGION METROPOLITANA DE SANTIAGO", "provincia": "Santiago", "totalapellido": 1, "totalcomuna": 142696, "prct_apellido": 7e-06, "freq_prov": 0.017023, "freq_reg": 0.018986, "cod_comuna": "13127"}, {"comuna": "IQUIQUE", "region": "01. REGION DE TARAPACA", "provincia": "Iquique", "totalapellido": 1, "totalcomuna": 167553, "prct_apellido": 6e-06, "freq_prov": 0.023146, "freq_reg": 0.02576, "cod_comuna": "01101"}]}, "ucancial": {"apellido": "UCANCIAL", "comunas": [{"comuna": "INDEPENDENCIA", "region": "13. REGION METROPOLITANA DE SANTIAGO", "provincia": "Santiago", "totalapellido": 1, "totalcomuna": 82629, "prct_apellido": 1.2e-05, "freq_prov": 0.017023, "freq_reg": 0.018986, "cod_comuna": "13108"}, {"comuna": "ESTACION CENTRAL", "region": "13. REGION METROPOLITANA DE SANTIAGO", "provincia": "Santiago", "totalapellido": 2, "totalcomuna": 127214, "prct_apellido": 1.6e-05, "freq_prov": 0.017023, "freq_reg": 0.018986, "cod_comuna": "13106"}]}, "ucar": {"apellido": "UCAR", "comunas": [{"comuna": "LO BARNECHEA", "region": "13. REGION METROPOLITANA DE SANTIAGO", "provincia": "Santiago", "totalapellido": 1, "totalcomuna": 82669, "prct_apellido": 1.2e-05, "freq_prov": 0.017023, "freq_reg": 0.018986, "cod_comuna": "13115"}]}, "ucariegue": {"apellido": "UCARIEGUE", "comunas": [{"comuna": "SANTIAGO", "region": "13. REGION METROPOLITANA DE SANTIAGO", "provincia": "Santiago", "totalapellido": 5, "totalcomuna": 340282, "prct_apellido": 1.5e-05, "freq_prov": 0.017023, "freq_reg": 0.018986, "cod_comuna": "13101"}, {"comuna": "ÑUÑOA", "region": "13. REGION METROPOLITANA DE SANTIAGO", "provincia": "Santiago", "totalapellido": 1, "totalcomuna": 197198, "prct_apellido": 5e-06, "freq_prov": 0.017023, "freq_reg": 0.018986, "cod_comuna": "13120"}]}, "uccellatore": {"apellido": "UCCELLATORE", "comunas": [{"comuna": "VALPARAISO", "region": "05. REGION DE VALPARAISO", "provincia": "Valparaíso", "totalapellido": 1, "totalcomuna": 290125, "prct_apellido": 3e-06, "freq_prov": 0.017698, "freq_reg": 0.029341, "cod_comuna": "05101"}]}, "uccelletti": {"apellido": "UCCELLETTI", "comunas": [{"comuna": "CALERA", "region": "05. REGION DE VALPARAISO", "provincia": "Quillota", "totalapellido": 1, "totalcomuna": 44980, "prct_apellido": 2.2e-05, "freq_prov": 0.079787, "freq_reg": 0.029341, "cod_comuna": "05502"}, {"comuna": "HUECHURABA", "region": "13. REGION METROPOLITANA DE SANTIAGO", "provincia": "Santiago", "totalapellido": 1, "totalcomuna": 73498, "prct_apellido": 1.4e-05, "freq_prov": 0.017023, "freq_reg": 0.018986, "cod_comuna": "13107"}, {"comuna": "LO BARNECHEA", "region": "13. REGION METROPOLITANA DE SANTIAGO", "provincia": "Santiago", "totalapellido": 1, "totalcomuna": 82669, "prct_apellido": 1.2e-05, "freq_prov": 0.017023, "freq_reg": 0.018986, "cod_comuna": "13115"}, {"comuna": "VIÑA DEL MAR", "region": "05. REGION DE VALPARAISO", "provincia": "Valparaíso", "totalapellido": 2, "totalcomuna": 301370, "prct_apellido": 7e-06, "freq_prov": 0.017698, "freq_reg": 0.029341, "cod_comuna": "05109"}]}, "uccelli": {"apellido": "UCCELLI", "comunas": [{"comuna": "LAS CONDES", "region": "13. REGION METROPOLITANA DE SANTIAGO", "provincia": "Santiago", "totalapellido": 1, "totalcomuna": 269517, "prct_apellido": 4e-06, "freq_prov": 0.017023, "freq_reg": 0.018986, "cod_comuna": "13114"}]}, "uccello": {"apellido": "UCCELLO", "comunas": [{"comuna": "VIÑA DEL MAR", "region": "05. REGION DE VALPARAISO", "provincia": "Valparaíso", "totalapellido": 1, "totalcomuna": 301370, "prct_apellido": 3e-06, "freq_prov": 0.017698, "freq_reg": 0.029341, "cod_comuna": "05109"}]}, "ucci": {"apellido": "UCCI", "comunas": [{"comuna": "VIÑA DEL MAR", "region": "05. REGION DE VALPARAISO", "provincia": "Valparaíso", "totalapellido": 1, "totalcomuna": 301370, "prct_apellido": 3e-06, "freq_prov": 0.017698, "freq_reg": 0.029341, "cod_comuna": "05109"}]}, "uceda": {"apellido": "UCEDA", "comunas": [{"comuna": "INDEPENDENCIA", "region": "13. REGION METROPOLITANA DE SANTIAGO", "provincia": "Santiago", "totalapellido": 5, "totalcomuna": 82629, "prct_apellido": 6.1e-05, "freq_prov": 0.017023, "freq_reg": 0.018986, "cod_comuna": "13108"}, {"comuna": "SANTIAGO", "region": "13. REGION METROPOLITANA DE SANTIAGO", "provincia": "Santiago", "totalapellido": 14, "totalcomuna": 340282, "prct_apellido": 4.1e-05, "freq_prov": 0.017023, "freq_reg": 0.018986, "cod_comuna": "13101"}, {"comuna": "QUINTA NORMAL", "region": "13. REGION METROPOLITANA DE SANTIAGO", "provincia": "Santiago", "totalapellido": 2, "totalcomuna": 102529, "prct_apellido": 2e-05, "freq_prov": 0.017023, "freq_reg": 0.018986, "cod_comuna": "13126"}, {"comuna": "SAN FELIPE", "region": "05. REGION DE VALPARAISO", "provincia": "San Felipe de Aconcagua", "totalapellido": 5, "totalcomuna": 60075, "prct_apellido": 8.3e-05, "freq_prov": 0.102948, "freq_reg": 0.029341, "cod_comuna": "05701"}, {"comuna": "ESTACION CENTRAL", "region": "13. REGION METROPOLITANA DE SANTIAGO", "provincia": "Santiago", "totalapellido": 3, "totalcomuna": 127214, "prct_apellido": 2.4e-05, "freq_prov": 0.017023, "freq_reg": 0.018986, "cod_comuna": "13106"}, {"comuna": "RECOLETA", "region": "13. REGION METROPOLITANA DE SANTIAGO", "provincia": "Santiago", "totalapellido": 4, "totalcomuna": 142696, "prct_apellido": 2.8e-05, "freq_prov": 0.017023, "freq_reg": 0.018986, "cod_comuna": "13127"}, {"comuna": "IQUIQUE", "region": "01. REGION DE TARAPACA", "provincia": "Iquique", "totalapellido": 6, "totalcomuna": 167553, "prct_apellido": 3.6e-05, "freq_prov": 0.023146, "freq_reg": 0.02576, "cod_comuna": "01101"}, {"comuna": "PROVIDENCIA", "region": "13. REGION METROPOLITANA DE SANTIAGO", "provincia": "Santiago", "totalapellido": 2, "totalcomuna": 170255, "prct_apellido": 1.2e-05, "freq_prov": 0.017023, "freq_reg": 0.018986, "cod_comuna": "13123"}, {"comuna": "VITACURA", "region": "13. REGION METROPOLITANA DE SANTIAGO", "provincia": "Santiago", "totalapellido": 4, "totalcomuna": 89311, "prct_apellido": 4.5e-05, "freq_prov": 0.017023, "freq_reg": 0.018986, "cod_comuna": "13132"}, {"comuna": "SAN MIGUEL", "region": "13. REGION METROPOLITANA DE SANTIAGO", "provincia": "Santiago", "totalapellido": 1, "totalcomuna": 105090, "prct_apellido": 1e-05, "freq_prov": 0.017023, "freq_reg": 0.018986, "cod_comuna": "13130"}, {"comuna": "CERRO NAVIA", "region": "13. REGION METROPOLITANA DE SANTIAGO", "provincia": "Santiago", "totalapellido": 1, "totalcomuna": 115479, "prct_apellido": 9e-06, "freq_prov": 0.017023, "freq_reg": 0.018986, "cod_comuna": "13103"}, {"comuna": "QUILPUE", "region": "05. REGION DE VALPARAISO", "provincia": "Marga Marga", "totalapellido": 1, "totalcomuna": 134448, "prct_apellido": 7e-06, "freq_prov": 0.034753, "freq_reg": 0.029341, "cod_comuna": "05801"}, {"comuna": "LAS CONDES", "region": "13. REGION METROPOLITANA DE SANTIAGO", "provincia": "Santiago", "totalapellido": 4, "totalcomuna": 269517, "prct_apellido": 1.5e-05, "freq_prov": 0.017023, "freq_reg": 0.018986, "cod_comuna": "13114"}, {"comuna": "EL BOSQUE", "region": "13. REGION METROPOLITANA DE SANTIAGO", "provincia": "Santiago", "totalapellido": 1, "totalcomuna": 137677, "prct_apellido": 7e-06, "freq_prov": 0.017023, "freq_reg": 0.018986, "cod_comuna": "13105"}, {"comuna": "PEÑALOLEN", "region": "13. REGION METROPOLITANA DE SANTIAGO", "provincia": "Santiago", "totalapellido": 2, "totalcomuna": 191707, "prct_apellido": 1e-05, "freq_prov": 0.017023, "freq_reg": 0.018986, "cod_comuna": "13122"}, {"comuna": "MAIPU", "region": "13. REGION METROPOLITANA DE SANTIAGO", "provincia": "Santiago", "totalapellido": 3, "totalcomuna": 389758, "prct_apellido": 8e-06, "freq_prov": 0.017023, "freq_reg": 0.018986, "cod_comuna": "13119"}]}, "uchal": {"apellido": "UCHAL", "comunas": [{"comuna": "FRESIA", "region": "10. REGION DE LOS LAGOS", "provincia": "Llanquihue", "totalapellido": 1, "totalcomuna": 12233, "prct_apellido": 8.2e-05, "freq_prov": 0.042563, "freq_reg": 0.052521, "cod_comuna": "10104"}, {"comuna": "VALDIVIA", "region": "14. REGION DE LOS RIOS", "provincia": "Valdivia", "totalapellido": 10, "totalcomuna": 138619, "prct_apellido": 7.2e-05, "freq_prov": 0.046113, "freq_reg": 0.0544, "cod_comuna": "14101"}, {"comuna": "LA UNION", "region": "14. REGION DE LOS RIOS", "provincia": "Ranco", "totalapellido": 1, "totalcomuna": 35754, "prct_apellido": 2.8e-05, "freq_prov": 0.112447, "freq_reg": 0.0544, "cod_comuna": "14201"}, {"comuna": "RECOLETA", "region": "13. REGION METROPOLITANA DE SANTIAGO", "provincia": "Santiago", "totalapellido": 1, "totalcomuna": 142696, "prct_apellido": 7e-06, "freq_prov": 0.017023, "freq_reg": 0.018986, "cod_comuna": "13127"}]}, "ucharico": {"apellido": "UCHARICO", "comunas": [{"comuna": "ARICA", "region": "15. REGION DE ARICA Y PARINACOTA", "provincia": "Arica", "totalapellido": 6, "totalcomuna": 180060, "prct_apellido": 3.3e-05, "freq_prov": 0.025797, "freq_reg": 0.026725, "cod_comuna": "15101"}, {"comuna": "IQUIQUE", "region": "01. REGION DE TARAPACA", "provincia": "Iquique", "totalapellido": 4, "totalcomuna": 167553, "prct_apellido": 2.4e-05, "freq_prov": 0.023146, "freq_reg": 0.02576, "cod_comuna": "01101"}, {"comuna": "LA FLORIDA", "region": "13. REGION METROPOLITANA DE SANTIAGO", "provincia": "Santiago", "totalapellido": 1, "totalcomuna": 307414, "prct_apellido": 3e-06, "freq_prov": 0.017023, "freq_reg": 0.018986, "cod_comuna": "13110"}]}, "ucharima": {"apellido": "UCHARIMA", "comunas": [{"comuna": "SAN JOAQUIN", "region": "13. REGION METROPOLITANA DE SANTIAGO", "provincia": "Santiago", "totalapellido": 1, "totalcomuna": 82325, "prct_apellido": 1.2e-05, "freq_prov": 0.017023, "freq_reg": 0.018986, "cod_comuna": "13129"}, {"comuna": "LO BARNECHEA", "region": "13. REGION METROPOLITANA DE SANTIAGO", "provincia": "Santiago", "totalapellido": 1, "totalcomuna": 82669, "prct_apellido": 1.2e-05, "freq_prov": 0.017023, "freq_reg": 0.018986, "cod_comuna": "13115"}]}, "uchasara": {"apellido": "UCHASARA", "comunas": [{"comuna": "RIO HURTADO", "region": "04. REGION DE COQUIMBO", "provincia": "Limarí", "totalapellido": 1, "totalcomuna": 4938, "prct_apellido": 0.000203, "freq_prov": 0.102708, "freq_reg": 0.046565, "cod_comuna": "04305"}, {"comuna": "MEJILLONES", "region": "02. REGION DE ANTOFAGASTA", "provincia": "Antofagasta", "totalapellido": 1, "totalcomuna": 10035, "prct_apellido": 0.0001, "freq_prov": 0.020817, "freq_reg": 0.025007, "cod_comuna": "02102"}, {"comuna": "LA CRUZ", "region": "05. REGION DE VALPARAISO", "provincia": "Quillota", "totalapellido": 2, "totalcomuna": 16329, "prct_apellido": 0.000122, "freq_prov": 0.079787, "freq_reg": 0.029341, "cod_comuna": "05504"}, {"comuna": "RECOLETA", "region": "13. REGION METROPOLITANA DE SANTIAGO", "provincia": "Santiago", "totalapellido": 4, "totalcomuna": 142696, "prct_apellido": 2.8e-05, "freq_prov": 0.017023, "freq_reg": 0.018986, "cod_comuna": "13127"}, {"comuna": "RENCA", "region": "13. REGION METROPOLITANA DE SANTIAGO", "provincia": "Santiago", "totalapellido": 3, "totalcomuna": 116730, "prct_apellido": 2.6e-05, "freq_prov": 0.017023, "freq_reg": 0.018986, "cod_comuna": "13128"}, {"comuna": "ESTACION CENTRAL", "region": "13. REGION METROPOLITANA DE SANTIAGO", "provincia": "Santiago", "totalapellido": 2, "totalcomuna": 127214, "prct_apellido": 1.6e-05, "freq_prov": 0.017023, "freq_reg": 0.018986, "cod_comuna": "13106"}, {"comuna": "IQUIQUE", "region": "01. REGION DE TARAPACA", "provincia": "Iquique", "totalapellido": 2, "totalcomuna": 167553, "prct_apellido": 1.2e-05, "freq_prov": 0.023146, "freq_reg": 0.02576, "cod_comuna": "01101"}, {"comuna": "OVALLE", "region": "04. REGION DE COQUIMBO", "provincia": "Limarí", "totalapellido": 1, "totalcomuna": 91832, "prct_apellido": 1.1e-05, "freq_prov": 0.102708, "freq_reg": 0.046565, "cod_comuna": "04301"}, {"comuna": "ANTOFAGASTA", "region": "02. REGION DE ANTOFAGASTA", "provincia": "Antofagasta", "totalapellido": 3, "totalcomuna": 286950, "prct_apellido": 1e-05, "freq_prov": 0.020817, "freq_reg": 0.025007, "cod_comuna": "02101"}, {"comuna": "CONCHALI", "region": "13. REGION METROPOLITANA DE SANTIAGO", "provincia": "Santiago", "totalapellido": 1, "totalcomuna": 118624, "prct_apellido": 8e-06, "freq_prov": 0.017023, "freq_reg": 0.018986, "cod_comuna": "13104"}, {"comuna": "LA PINTANA", "region": "13. REGION METROPOLITANA DE SANTIAGO", "provincia": "Santiago", "totalapellido": 1, "totalcomuna": 139100, "prct_apellido": 7e-06, "freq_prov": 0.017023, "freq_reg": 0.018986, "cod_comuna": "13112"}, {"comuna": "ARICA", "region": "15. REGION DE ARICA Y PARINACOTA", "provincia": "Arica", "totalapellido": 2, "totalcomuna": 180060, "prct_apellido": 1.1e-05, "freq_prov": 0.025797, "freq_reg": 0.026725, "cod_comuna": "15101"}, {"comuna": "SANTIAGO", "region": "13. REGION METROPOLITANA DE SANTIAGO", "provincia": "Santiago", "totalapellido": 2, "totalcomuna": 340282, "prct_apellido": 6e-06, "freq_prov": 0.017023, "freq_reg": 0.018986, "cod_comuna": "13101"}, {"comuna": "MAIPU", "region": "13. REGION METROPOLITANA DE SANTIAGO", "provincia": "Santiago", "totalapellido": 1, "totalcomuna": 389758, "prct_apellido": 3e-06, "freq_prov": 0.017023, "freq_reg": 0.018986, "cod_comuna": "13119"}]}, "uchatoma": {"apellido": "UCHATOMA", "comunas": [{"comuna": "SANTIAGO", "region": "13. REGION METROPOLITANA DE SANTIAGO", "provincia": "Santiago", "totalapellido": 1, "totalcomuna": 340282, "prct_apellido": 3e-06, "freq_prov": 0.017023, "freq_reg": 0.018986, "cod_comuna": "13101"}]}, "uchida": {"apellido": "UCHIDA", "comunas": [{"comuna": "LO BARNECHEA", "region": "13. REGION METROPOLITANA DE SANTIAGO", "provincia": "Santiago", "totalapellido": 7, "totalcomuna": 82669, "prct_apellido": 8.5e-05, "freq_prov": 0.017023, "freq_reg": 0.018986, "cod_comuna": "13115"}, {"comuna": "TOCOPILLA", "region": "02. REGION DE ANTOFAGASTA", "provincia": "Tocopilla", "totalapellido": 2, "totalcomuna": 22335, "prct_apellido": 9e-05, "freq_prov": 0.11764, "freq_reg": 0.025007, "cod_comuna": "02301"}, {"comuna": "LAS CONDES", "region": "13. REGION METROPOLITANA DE SANTIAGO", "provincia": "Santiago", "totalapellido": 11, "totalcomuna": 269517, "prct_apellido": 4.1e-05, "freq_prov": 0.017023, "freq_reg": 0.018986, "cod_comuna": "13114"}, {"comuna": "QUILPUE", "region": "05. REGION DE VALPARAISO", "provincia": "Marga Marga", "totalapellido": 6, "totalcomuna": 134448, "prct_apellido": 4.5e-05, "freq_prov": 0.034753, "freq_reg": 0.029341, "cod_comuna": "05801"}, {"comuna": "COQUIMBO", "region": "04. REGION DE COQUIMBO", "provincia": "Elqui", "totalapellido": 2, "totalcomuna": 167854, "prct_apellido": 1.2e-05, "freq_prov": 0.034381, "freq_reg": 0.046565, "cod_comuna": "04102"}, {"comuna": "LA REINA", "region": "13. REGION METROPOLITANA DE SANTIAGO", "provincia": "Santiago", "totalapellido": 1, "totalcomuna": 91556, "prct_apellido": 1.1e-05, "freq_prov": 0.017023, "freq_reg": 0.018986, "cod_comuna": "13113"}, {"comuna": "VILLA ALEMANA", "region": "05. REGION DE VALPARAISO", "provincia": "Marga Marga", "totalapellido": 1, "totalcomuna": 98544, "prct_apellido": 1e-05, "freq_prov": 0.034753, "freq_reg": 0.029341, "cod_comuna": "05804"}, {"comuna": "PROVIDENCIA", "region": "13. REGION METROPOLITANA DE SANTIAGO", "provincia": "Santiago", "totalapellido": 1, "totalcomuna": 170255, "prct_apellido": 6e-06, "freq_prov": 0.017023, "freq_reg": 0.018986, "cod_comuna": "13123"}, {"comuna": "ÑUÑOA", "region": "13. REGION METROPOLITANA DE SANTIAGO", "provincia": "Santiago", "totalapellido": 1, "totalcomuna": 197198, "prct_apellido": 5e-06, "freq_prov": 0.017023, "freq_reg": 0.018986, "cod_comuna": "13120"}, {"comuna": "SANTIAGO", "region": "13. REGION METROPOLITANA DE SANTIAGO", "provincia": "Santiago", "totalapellido": 1, "totalcomuna": 340282, "prct_apellido": 3e-06, "freq_prov": 0.017023, "freq_reg": 0.018986, "cod_comuna": "13101"}, {"comuna": "MAIPU", "region": "13. REGION METROPOLITANA DE SANTIAGO", "provincia": "Santiago", "totalapellido": 2, "totalcomuna": 389758, "prct_apellido": 5e-06, "freq_prov": 0.017023, "freq_reg": 0.018986, "cod_comuna": "13119"}]}, "uchikata": {"apellido": "UCHIKATA", "comunas": [{"comuna": "SANTIAGO", "region": "13. REGION METROPOLITANA DE SANTIAGO", "provincia": "Santiago", "totalapellido": 1, "totalcomuna": 340282, "prct_apellido": 3e-06, "freq_prov": 0.017023, "freq_reg": 0.018986, "cod_comuna": "13101"}]}, "uchillan": {"apellido": "UCHILLAN", "comunas": [{"comuna": "LO PRADO", "region": "13. REGION METROPOLITANA DE SANTIAGO", "provincia": "Santiago", "totalapellido": 1, "totalcomuna": 88885, "prct_apellido": 1.1e-05, "freq_prov": 0.017023, "freq_reg": 0.018986, "cod_comuna": "13117"}, {"comuna": "LA SERENA", "region": "04. REGION DE COQUIMBO", "provincia": "Elqui", "totalapellido": 3, "totalcomuna": 174853, "prct_apellido": 1.7e-05, "freq_prov": 0.034381, "freq_reg": 0.046565, "cod_comuna": "04101"}, {"comuna": "SANTIAGO", "region": "13. REGION METROPOLITANA DE SANTIAGO", "provincia": "Santiago", "totalapellido": 1, "totalcomuna": 340282, "prct_apellido": 3e-06, "freq_prov": 0.017023, "freq_reg": 0.018986, "cod_comuna": "13101"}]}, "uchima": {"apellido": "UCHIMA", "comunas": [{"comuna": "SANTIAGO", "region": "13. REGION METROPOLITANA DE SANTIAGO", "provincia": "Santiago", "totalapellido": 2, "totalcomuna": 340282, "prct_apellido": 6e-06, "freq_prov": 0.017023, "freq_reg": 0.018986, "cod_comuna": "13101"}, {"comuna": "PROVIDENCIA", "region": "13. REGION METROPOLITANA DE SANTIAGO", "provincia": "Santiago", "totalapellido": 1, "totalcomuna": 170255, "prct_apellido": 6e-06, "freq_prov": 0.017023, "freq_reg": 0.018986, "cod_comuna": "13123"}]}, "uchimura": {"apellido": "UCHIMURA", "comunas": [{"comuna": "COPIAPO", "region": "03. REGION DE ATACAMA", "provincia": "Copiapó", "totalapellido": 1, "totalcomuna": 123973, "prct_apellido": 8e-06, "freq_prov": 0.043922, "freq_reg": 0.058317, "cod_comuna": "03101"}, {"comuna": "VIÑA DEL MAR", "region": "05. REGION DE VALPARAISO", "provincia": "Valparaíso", "totalapellido": 2, "totalcomuna": 301370, "prct_apellido": 7e-06, "freq_prov": 0.017698, "freq_reg": 0.029341, "cod_comuna": "05109"}]}, "uchino": {"apellido": "UCHINO", "comunas": [{"comuna": "LAS CONDES", "region": "13. REGION METROPOLITANA DE SANTIAGO", "provincia": "Santiago", "totalapellido": 4, "totalcomuna": 269517, "prct_apellido": 1.5e-05, "freq_prov": 0.017023, "freq_reg": 0.018986, "cod_comuna": "13114"}]}, "uchiyama": {"apellido": "UCHIYAMA", "comunas": [{"comuna": "LAS CONDES", "region": "13. REGION METROPOLITANA DE SANTIAGO", "provincia": "Santiago", "totalapellido": 1, "totalcomuna": 269517, "prct_apellido": 4e-06, "freq_prov": 0.017023, "freq_reg": 0.018986, "cod_comuna": "13114"}]}, "uchoa": {"apellido": "UCHOA", "comunas": [{"comuna": "BULNES", "region": "16. REGION DE ÑUBLE", "provincia": "Diguillín", "totalapellido": 1, "totalcomuna": 20535, "prct_apellido": 4.9e-05, "freq_prov": 0.065041, "freq_reg": 0.0859, "cod_comuna": "16102"}, {"comuna": "CONCHALI", "region": "13. REGION METROPOLITANA DE SANTIAGO", "provincia": "Santiago", "totalapellido": 11, "totalcomuna": 118624, "prct_apellido": 9.3e-05, "freq_prov": 0.017023, "freq_reg": 0.018986, "cod_comuna": "13104"}, {"comuna": "RECOLETA", "region": "13. REGION METROPOLITANA DE SANTIAGO", "provincia": "Santiago", "totalapellido": 7, "totalcomuna": 142696, "prct_apellido": 4.9e-05, "freq_prov": 0.017023, "freq_reg": 0.018986, "cod_comuna": "13127"}, {"comuna": "QUILICURA", "region": "13. REGION METROPOLITANA DE SANTIAGO", "provincia": "Santiago", "totalapellido": 3, "totalcomuna": 139914, "prct_apellido": 2.1e-05, "freq_prov": 0.017023, "freq_reg": 0.018986, "cod_comuna": "13125"}, {"comuna": "HUECHURABA", "region": "13. REGION METROPOLITANA DE SANTIAGO", "provincia": "Santiago", "totalapellido": 4, "totalcomuna": 73498, "prct_apellido": 5.4e-05, "freq_prov": 0.017023, "freq_reg": 0.018986, "cod_comuna": "13107"}, {"comuna": "QUINTA NORMAL", "region": "13. REGION METROPOLITANA DE SANTIAGO", "provincia": "Santiago", "totalapellido": 3, "totalcomuna": 102529, "prct_apellido": 2.9e-05, "freq_prov": 0.017023, "freq_reg": 0.018986, "cod_comuna": "13126"}]}, "uchofen": {"apellido": "UCHOFEN", "comunas": [{"comuna": "RECOLETA", "region": "13. REGION METROPOLITANA DE SANTIAGO", "provincia": "Santiago", "totalapellido": 1, "totalcomuna": 142696, "prct_apellido": 7e-06, "freq_prov": 0.017023, "freq_reg": 0.018986, "cod_comuna": "13127"}, {"comuna": "SANTIAGO", "region": "13. REGION METROPOLITANA DE SANTIAGO", "provincia": "Santiago", "totalapellido": 4, "totalcomuna": 340282, "prct_apellido": 1.2e-05, "freq_prov": 0.017023, "freq_reg": 0.018986, "cod_comuna": "13101"}]}, "uchpas": {"apellido": "UCHPAS", "comunas": [{"comuna": "LAS CONDES", "region": "13. REGION METROPOLITANA DE SANTIAGO", "provincia": "Santiago", "totalapellido": 1, "totalcomuna": 269517, "prct_apellido": 4e-06, "freq_prov": 0.017023, "freq_reg": 0.018986, "cod_comuna": "13114"}]}, "uchuipoma": {"apellido": "UCHUIPOMA", "comunas": [{"comuna": "PEÑALOLEN", "region": "13. REGION METROPOLITANA DE SANTIAGO", "provincia": "Santiago", "totalapellido": 5, "totalcomuna": 191707, "prct_apellido": 2.6e-05, "freq_prov": 0.017023, "freq_reg": 0.018986, "cod_comuna": "13122"}]}, "uchupe": {"apellido": "UCHUPE", "comunas": [{"comuna": "LO BARNECHEA", "region": "13. REGION METROPOLITANA DE SANTIAGO", "provincia": "Santiago", "totalapellido": 1, "totalcomuna": 82669, "prct_apellido": 1.2e-05, "freq_prov": 0.017023, "freq_reg": 0.018986, "cod_comuna": "13115"}]}, "uchuya": {"apellido": "UCHUYA", "comunas": [{"comuna": "CALAMA", "region": "02. REGION DE ANTOFAGASTA", "provincia": "El Loa", "totalapellido": 3, "totalcomuna": 132333, "prct_apellido": 2.3e-05, "freq_prov": 0.035053, "freq_reg": 0.025007, "cod_comuna": "02201"}, {"comuna": "SAN BERNARDO", "region": "13. REGION METROPOLITANA DE SANTIAGO", "provincia": "Maipo", "totalapellido": 1, "totalcomuna": 228196, "prct_apellido": 4e-06, "freq_prov": 0.033289, "freq_reg": 0.018986, "cod_comuna": "13401"}, {"comuna": "MAIPU", "region": "13. REGION METROPOLITANA DE SANTIAGO", "provincia": "Santiago", "totalapellido": 1, "totalcomuna": 389758, "prct_apellido": 3e-06, "freq_prov": 0.017023, "freq_reg": 0.018986, "cod_comuna": "13119"}]}, "uchuypoma": {"apellido": "UCHUYPOMA", "comunas": [{"comuna": "INDEPENDENCIA", "region": "13. REGION METROPOLITANA DE SANTIAGO", "provincia": "Santiago", "totalapellido": 1, "totalcomuna": 82629, "prct_apellido": 1.2e-05, "freq_prov": 0.017023, "freq_reg": 0.018986, "cod_comuna": "13108"}]}, "ucke": {"apellido": "UCKE", "comunas": [{"comuna": "PROVIDENCIA", "region": "13. REGION METROPOLITANA DE SANTIAGO", "provincia": "Santiago", "totalapellido": 1, "totalcomuna": 170255, "prct_apellido": 6e-06, "freq_prov": 0.017023, "freq_reg": 0.018986, "cod_comuna": "13123"}]}, "ucros": {"apellido": "UCROS", "comunas": [{"comuna": "ANTOFAGASTA", "region": "02. REGION DE ANTOFAGASTA", "provincia": "Antofagasta", "totalapellido": 3, "totalcomuna": 286950, "prct_apellido": 1e-05, "freq_prov": 0.020817, "freq_reg": 0.025007, "cod_comuna": "02101"}, {"comuna": "ÑUÑOA", "region": "13. REGION METROPOLITANA DE SANTIAGO", "provincia": "Santiago", "totalapellido": 1, "totalcomuna": 197198, "prct_apellido": 5e-06, "freq_prov": 0.017023, "freq_reg": 0.018986, "cod_comuna": "13120"}, {"comuna": "SAN BERNARDO", "region": "13. REGION METROPOLITANA DE SANTIAGO", "provincia": "Maipo", "totalapellido": 1, "totalcomuna": 228196, "prct_apellido": 4e-06, "freq_prov": 0.033289, "freq_reg": 0.018986, "cod_comuna": "13401"}]}, "ucsa": {"apellido": "UCSA", "comunas": [{"comuna": "ESTACION CENTRAL", "region": "13. REGION METROPOLITANA DE SANTIAGO", "provincia": "Santiago", "totalapellido": 3, "totalcomuna": 127214, "prct_apellido": 2.4e-05, "freq_prov": 0.017023, "freq_reg": 0.018986, "cod_comuna": "13106"}, {"comuna": "RECOLETA", "region": "13. REGION METROPOLITANA DE SANTIAGO", "provincia": "Santiago", "totalapellido": 1, "totalcomuna": 142696, "prct_apellido": 7e-06, "freq_prov": 0.017023, "freq_reg": 0.018986, "cod_comuna": "13127"}]}, "uculmana": {"apellido": "UCULMANA", "comunas": [{"comuna": "QUINTA NORMAL", "region": "13. REGION METROPOLITANA DE SANTIAGO", "provincia": "Santiago", "totalapellido": 4, "totalcomuna": 102529, "prct_apellido": 3.9e-05, "freq_prov": 0.017023, "freq_reg": 0.018986, "cod_comuna": "13126"}, {"comuna": "SANTIAGO", "region": "13. REGION METROPOLITANA DE SANTIAGO", "provincia": "Santiago", "totalapellido": 5, "totalcomuna": 340282, "prct_apellido": 1.5e-05, "freq_prov": 0.017023, "freq_reg": 0.018986, "cod_comuna": "13101"}]}, "ucuntala": {"apellido": "UCUNTALA", "comunas": [{"comuna": "IQUIQUE", "region": "01. REGION DE TARAPACA", "provincia": "Iquique", "totalapellido": 1, "totalcomuna": 167553, "prct_apellido": 6e-06, "freq_prov": 0.023146, "freq_reg": 0.02576, "cod_comuna": "01101"}]}}